{"firstName":"Neha","lastName":"Rao","graduation":"05/2020","major":"Information Science","minor":"Business","hometown":"Northern Virginia","github":"","linkedin":"https://www.linkedin.com/in/neha-rao-75a5bb133/","medium":"","website":"","portfolio":"","about":"Other than being a part of this project team, I'm Musical Director of Cornell's Original Musical Theatre Troupe, Anything Goes. I love to sing, play guitar, and Zumba in my free time.","teams":"Shout 1 year Business 1+ years","What is your role on the team?":"Product Manager","Is there any information on this section of the form that you would prefer not be on the website under your name?":""}
